pptsmith/__init__.py
pptsmith/cli.py
pptsmith-1.0.0.dist-info/METADATA
pptsmith-1.0.0.dist-info/WHEEL
pptsmith-1.0.0.dist-info/entry_points.txt
pptsmith-1.0.0.dist-info/top_level.txt
pptsmith-1.0.0.dist-info/RECORD
