Metadata-Version: 2.4
Name: pptsmith
Version: 1.0.0
Summary: 从 Markdown 生成 PowerPoint 演示文稿的工具
Author-email: poiet <pioet@aliyun.com>
License: MIT
Project-URL: Homepage, https://github.com/pioet/pptsmith
Project-URL: Repository, https://github.com/pioet/pptsmith
Project-URL: Issues, https://github.com/pioet/pptsmith/issues
Keywords: ppt,powerpoint,markdown,presentation,slide
Classifier: Development Status :: 3 - Alpha
Classifier: Intended Audience :: Developers
Classifier: License :: OSI Approved :: MIT License
Classifier: Programming Language :: Python :: 3
Classifier: Programming Language :: Python :: 3.9
Classifier: Programming Language :: Python :: 3.10
Classifier: Programming Language :: Python :: 3.11
Classifier: Programming Language :: Python :: 3.12
Requires-Python: >=3.9
Requires-Dist: python-pptx>=0.6.21
Requires-Dist: click>=8.0.0
Provides-Extra: dev
Requires-Dist: pytest>=7.0.0; extra == "dev"
Requires-Dist: black>=22.0.0; extra == "dev"
Requires-Dist: ruff>=0.1.0; extra == "dev"
